<annotation>
	<folder>512lighter</folder>
	<filename>512images (58).jpg</filename>
	<path>E:\512lighter\512images (58).jpg</path>
	<source>
		<database>Unknown</database>
	</source>
	<size>
		<width>512</width>
		<height>512</height>
		<depth>3</depth>
	</size>
	<segmented>0</segmented>
	<object>
		<name>fire</name>
		<pose>Unspecified</pose>
		<truncated>0</truncated>
		<difficult>0</difficult>
		<bndbox>
			<xmin>209</xmin>
			<ymin>181</ymin>
			<xmax>243</xmax>
			<ymax>288</ymax>
		</bndbox>
	</object>
<object>
		<name>fire</name>
		<pose>Unspecified</pose>
		<truncated>0</truncated>
		<difficult>0</difficult>
		<bndbox>
			<xmin>740</xmin>
			<ymin>11</ymin>
			<xmax>828</xmax>
			<ymax>216</ymax>
		</bndbox>
	</object>
<object>
		<name>fire</name>
		<pose>Unspecified</pose>
		<truncated>0</truncated>
		<difficult>0</difficult>
		<bndbox>
			<xmin>175</xmin>
			<ymin>537</ymin>
			<xmax>227</xmax>
			<ymax>682</ymax>
		</bndbox>
	</object>
<object>
		<name>fire</name>
		<pose>Unspecified</pose>
		<truncated>1</truncated>
		<difficult>0</difficult>
		<bndbox>
			<xmin>593</xmin>
			<ymin>513</ymin>
			<xmax>644</xmax>
			<ymax>721</ymax>
		</bndbox>
	</object>
<object>
		<name>fire</name>
		<pose>Unspecified</pose>
		<truncated>0</truncated>
		<difficult>0</difficult>
		<bndbox>
			<xmin>1257</xmin>
			<ymin>103</ymin>
			<xmax>1310</xmax>
			<ymax>285</ymax>
		</bndbox>
	</object>
<object>
		<name>fire</name>
		<pose>Unspecified</pose>
		<truncated>0</truncated>
		<difficult>0</difficult>
		<bndbox>
			<xmin>1734</xmin>
			<ymin>164</ymin>
			<xmax>1765</xmax>
			<ymax>236</ymax>
		</bndbox>
	</object>
<object>
		<name>fire</name>
		<pose>Unspecified</pose>
		<truncated>0</truncated>
		<difficult>0</difficult>
		<bndbox>
			<xmin>1254</xmin>
			<ymin>569</ymin>
			<xmax>1303</xmax>
			<ymax>812</ymax>
		</bndbox>
	</object>
<object>
		<name>fire</name>
		<pose>Unspecified</pose>
		<truncated>0</truncated>
		<difficult>0</difficult>
		<bndbox>
			<xmin>1796</xmin>
			<ymin>551</ymin>
			<xmax>1832</xmax>
			<ymax>699</ymax>
		</bndbox>
	</object>
<object>
		<name>fire</name>
		<pose>Unspecified</pose>
		<truncated>0</truncated>
		<difficult>0</difficult>
		<bndbox>
			<xmin>136</xmin>
			<ymin>1099</ymin>
			<xmax>171</xmax>
			<ymax>1224</ymax>
		</bndbox>
	</object>
<object>
		<name>fire</name>
		<pose>Unspecified</pose>
		<truncated>0</truncated>
		<difficult>0</difficult>
		<bndbox>
			<xmin>696</xmin>
			<ymin>1105</ymin>
			<xmax>754</xmax>
			<ymax>1360</ymax>
		</bndbox>
	</object>
<object>
		<name>fire</name>
		<pose>Unspecified</pose>
		<truncated>0</truncated>
		<difficult>0</difficult>
		<bndbox>
			<xmin>269</xmin>
			<ymin>1717</ymin>
			<xmax>303</xmax>
			<ymax>1824</ymax>
		</bndbox>
	</object>
<object>
		<name>fire</name>
		<pose>Unspecified</pose>
		<truncated>0</truncated>
		<difficult>0</difficult>
		<bndbox>
			<xmin>708</xmin>
			<ymin>1547</ymin>
			<xmax>796</xmax>
			<ymax>1752</ymax>
		</bndbox>
	</object>
<object>
		<name>fire</name>
		<pose>Unspecified</pose>
		<truncated>0</truncated>
		<difficult>0</difficult>
		<bndbox>
			<xmin>1099</xmin>
			<ymin>1189</ymin>
			<xmax>1285</xmax>
			<ymax>1375</ymax>
		</bndbox>
	</object>
<object>
		<name>fire</name>
		<pose>Unspecified</pose>
		<truncated>0</truncated>
		<difficult>0</difficult>
		<bndbox>
			<xmin>1733</xmin>
			<ymin>1085</ymin>
			<xmax>1848</xmax>
			<ymax>1478</ymax>
		</bndbox>
	</object>
<object>
		<name>fire</name>
		<pose>Unspecified</pose>
		<truncated>0</truncated>
		<difficult>0</difficult>
		<bndbox>
			<xmin>1214</xmin>
			<ymin>1607</ymin>
			<xmax>1307</xmax>
			<ymax>1883</ymax>
		</bndbox>
	</object>
<object>
		<name>fire</name>
		<pose>Unspecified</pose>
		<truncated>0</truncated>
		<difficult>0</difficult>
		<bndbox>
			<xmin>1803</xmin>
			<ymin>1718</ymin>
			<xmax>1841</xmax>
			<ymax>1848</ymax>
		</bndbox>
	</object>
</annotation>