<annotation>
	<folder>Annotations</folder>
	<filename>img-212.jpg</filename>
	<path>/home/epc/code/data/Annotations/img-212.jpg</path>
	<source>
		<database>Unknown</database>
	</source>
	<size>
		<width>2000</width>
		<height>1340</height>
		<depth>3</depth>
	</size>
	<segmented>0</segmented>
	<object>
		<name>fire</name>
		<pose>Unspecified</pose>
		<truncated>0</truncated>
		<difficult>0</difficult>
		<bndbox>
			<xmin>1250</xmin>
			<ymin>460</ymin>
			<xmax>1880</xmax>
			<ymax>899</ymax>
		</bndbox>
	</object>
</annotation>
