<annotation>
	<folder>image</folder>
	<filename>img460.jpg</filename>
	<path>/home/epc/code/data/fire/image/img460.jpg</path>
	<source>
		<database>Unknown</database>
	</source>
	<size>
		<width>275</width>
		<height>183</height>
		<depth>3</depth>
	</size>
	<segmented>0</segmented>
	<object>
		<name>fire</name>
		<pose>Unspecified</pose>
		<truncated>0</truncated>
		<difficult>0</difficult>
		<bndbox>
			<xmin>65</xmin>
			<ymin>74</ymin>
			<xmax>150</xmax>
			<ymax>128</ymax>
		</bndbox>
	</object>
</annotation>
