<?xml version='1.0' encoding='utf-8'?>
<annotation>
	<folder>Annotations</folder>
	<filename>img681.jpg</filename>
	<path>/home/epc/code/data/Annotations/img681.jpg</path>
	<source>
		<database>Unknown</database>
	</source>
	<size>
		<width>447</width>
		<height>299</height>
		<depth>3</depth>
	</size>
	<segmented>0</segmented>
	<object>
		<name>fire</name>
		<pose>Unspecified</pose>
		<truncated>0</truncated>
		<difficult>0</difficult>
		<bndbox>
			<xmin>155</xmin>
			<ymin>125</ymin>
			<xmax>264</xmax>
			<ymax>229</ymax>
		</bndbox>
	</object>
	</annotation>