<annotation>
	<folder>office_get_light</folder>
	<filename>office_146.jpg</filename>
	<path>E:\office_get_light\office_146.jpg</path>
	<source>
		<database>Unknown</database>
	</source>
	<size>
		<width>1016</width>
		<height>760</height>
		<depth>3</depth>
	</size>
	<segmented>0</segmented>
	<object>
		<name>fire</name>
		<pose>Unspecified</pose>
		<truncated>0</truncated>
		<difficult>0</difficult>
		<bndbox>
			<xmin>639</xmin>
			<ymin>476</ymin>
			<xmax>657</xmax>
			<ymax>496</ymax>
		</bndbox>
	</object>
</annotation>
